plum/__init__.py
plum/_code_injector.py
plum/_default.py
plum/_getbytes.py
plum/_typing.py
plum/array.py
plum/attrdict.py
plum/bigendian.py
plum/buffer.py
plum/bytes.py
plum/conformance.py
plum/data.py
plum/decimal.py
plum/dump.py
plum/enum.py
plum/exceptions.py
plum/flag.py
plum/float.py
plum/int.py
plum/ipaddress.py
plum/items.py
plum/littleendian.py
plum/none.py
plum/object.py
plum/optional.py
plum/py.typed
plum/sized.py
plum/str.py
plum/transform.py
plum/utilities.py
plum/view.py
plum/bitfields/__init__.py
plum/bitfields/bitfield.py
plum/bitfields/code_maker.py
plum/bitfields/meta.py
plum/structure/__init__.py
plum/structure/bitfield_member.py
plum/structure/code_maker.py
plum/structure/dimmed_member.py
plum/structure/member.py
plum/structure/meta.py
plum/structure/sized_member.py
plum/structure/structureview.py
plum_py-0.8.7.dist-info/LICENSE
plum_py-0.8.7.dist-info/METADATA
plum_py-0.8.7.dist-info/WHEEL
plum_py-0.8.7.dist-info/top_level.txt
plum_py-0.8.7.dist-info/zip-safe
plum_py-0.8.7.dist-info/RECORD
